{
  "frames": {
    "12.png": {
      "frame": {
        "x": 0,
        "y": 0,
        "w": 92,
        "h": 80
      },
      "rotated": false,
      "trimmed": true,
      "spriteSourceSize": {
        "x": 4,
        "y": 16,
        "w": 92,
        "h": 80
      },
      "sourceSize": {
        "w": 100,
        "h": 100
      },
      "pivot": {
        "x": 0.5,
        "y": 0.5
      }
    },
    "09.png": {
      "frame": {
        "x": 92,
        "y": 0,
        "w": 90,
        "h": 80
      },
      "rotated": false,
      "trimmed": true,
      "spriteSourceSize": {
        "x": 6,
        "y": 16,
        "w": 90,
        "h": 80
      },
      "sourceSize": {
        "w": 100,
        "h": 100
      },
      "pivot": {
        "x": 0.5,
        "y": 0.5
      }
    },
    "10.png": {
      "frame": {
        "x": 182,
        "y": 0,
        "w": 90,
        "h": 80
      },
      "rotated": false,
      "trimmed": true,
      "spriteSourceSize": {
        "x": 6,
        "y": 16,
        "w": 90,
        "h": 80
      },
      "sourceSize": {
        "w": 100,
        "h": 100
      },
      "pivot": {
        "x": 0.5,
        "y": 0.5
      }
    },
    "11.png": {
      "frame": {
        "x": 272,
        "y": 0,
        "w": 90,
        "h": 80
      },
      "rotated": false,
      "trimmed": true,
      "spriteSourceSize": {
        "x": 6,
        "y": 16,
        "w": 90,
        "h": 80
      },
      "sourceSize": {
        "w": 100,
        "h": 100
      },
      "pivot": {
        "x": 0.5,
        "y": 0.5
      }
    },
    "13.png": {
      "frame": {
        "x": 362,
        "y": 0,
        "w": 90,
        "h": 80
      },
      "rotated": false,
      "trimmed": true,
      "spriteSourceSize": {
        "x": 6,
        "y": 16,
        "w": 90,
        "h": 80
      },
      "sourceSize": {
        "w": 100,
        "h": 100
      },
      "pivot": {
        "x": 0.5,
        "y": 0.5
      }
    },
    "14.png": {
      "frame": {
        "x": 452,
        "y": 0,
        "w": 90,
        "h": 78
      },
      "rotated": false,
      "trimmed": true,
      "spriteSourceSize": {
        "x": 6,
        "y": 18,
        "w": 90,
        "h": 78
      },
      "sourceSize": {
        "w": 100,
        "h": 100
      },
      "pivot": {
        "x": 0.5,
        "y": 0.5
      }
    },
    "15.png": {
      "frame": {
        "x": 542,
        "y": 0,
        "w": 90,
        "h": 76
      },
      "rotated": false,
      "trimmed": true,
      "spriteSourceSize": {
        "x": 6,
        "y": 18,
        "w": 90,
        "h": 76
      },
      "sourceSize": {
        "w": 100,
        "h": 100
      },
      "pivot": {
        "x": 0.5,
        "y": 0.5
      }
    },
    "16.png": {
      "frame": {
        "x": 632,
        "y": 0,
        "w": 90,
        "h": 76
      },
      "rotated": false,
      "trimmed": true,
      "spriteSourceSize": {
        "x": 6,
        "y": 18,
        "w": 90,
        "h": 76
      },
      "sourceSize": {
        "w": 100,
        "h": 100
      },
      "pivot": {
        "x": 0.5,
        "y": 0.5
      }
    },
    "17.png": {
      "frame": {
        "x": 722,
        "y": 0,
        "w": 90,
        "h": 74
      },
      "rotated": false,
      "trimmed": true,
      "spriteSourceSize": {
        "x": 6,
        "y": 20,
        "w": 90,
        "h": 74
      },
      "sourceSize": {
        "w": 100,
        "h": 100
      },
      "pivot": {
        "x": 0.5,
        "y": 0.5
      }
    },
    "18.png": {
      "frame": {
        "x": 812,
        "y": 0,
        "w": 90,
        "h": 74
      },
      "rotated": false,
      "trimmed": true,
      "spriteSourceSize": {
        "x": 6,
        "y": 20,
        "w": 90,
        "h": 74
      },
      "sourceSize": {
        "w": 100,
        "h": 100
      },
      "pivot": {
        "x": 0.5,
        "y": 0.5
      }
    },
    "19.png": {
      "frame": {
        "x": 902,
        "y": 0,
        "w": 90,
        "h": 74
      },
      "rotated": false,
      "trimmed": true,
      "spriteSourceSize": {
        "x": 6,
        "y": 20,
        "w": 90,
        "h": 74
      },
      "sourceSize": {
        "w": 100,
        "h": 100
      },
      "pivot": {
        "x": 0.5,
        "y": 0.5
      }
    },
    "08.png": {
      "frame": {
        "x": 722,
        "y": 74,
        "w": 88,
        "h": 80
      },
      "rotated": false,
      "trimmed": true,
      "spriteSourceSize": {
        "x": 8,
        "y": 16,
        "w": 88,
        "h": 80
      },
      "sourceSize": {
        "w": 100,
        "h": 100
      },
      "pivot": {
        "x": 0.5,
        "y": 0.5
      }
    },
    "07.png": {
      "frame": {
        "x": 542,
        "y": 76,
        "w": 88,
        "h": 76
      },
      "rotated": false,
      "trimmed": true,
      "spriteSourceSize": {
        "x": 8,
        "y": 18,
        "w": 88,
        "h": 76
      },
      "sourceSize": {
        "w": 100,
        "h": 100
      },
      "pivot": {
        "x": 0.5,
        "y": 0.5
      }
    },
    "20.png": {
      "frame": {
        "x": 452,
        "y": 78,
        "w": 88,
        "h": 74
      },
      "rotated": false,
      "trimmed": true,
      "spriteSourceSize": {
        "x": 8,
        "y": 20,
        "w": 88,
        "h": 74
      },
      "sourceSize": {
        "w": 100,
        "h": 100
      },
      "pivot": {
        "x": 0.5,
        "y": 0.5
      }
    },
    "06.png": {
      "frame": {
        "x": 630,
        "y": 76,
        "w": 86,
        "h": 76
      },
      "rotated": false,
      "trimmed": true,
      "spriteSourceSize": {
        "x": 10,
        "y": 18,
        "w": 86,
        "h": 76
      },
      "sourceSize": {
        "w": 100,
        "h": 100
      },
      "pivot": {
        "x": 0.5,
        "y": 0.5
      }
    },
    "05.png": {
      "frame": {
        "x": 810,
        "y": 74,
        "w": 84,
        "h": 74
      },
      "rotated": false,
      "trimmed": true,
      "spriteSourceSize": {
        "x": 10,
        "y": 18,
        "w": 84,
        "h": 74
      },
      "sourceSize": {
        "w": 100,
        "h": 100
      },
      "pivot": {
        "x": 0.5,
        "y": 0.5
      }
    },
    "21.png": {
      "frame": {
        "x": 894,
        "y": 74,
        "w": 84,
        "h": 70
      },
      "rotated": false,
      "trimmed": true,
      "spriteSourceSize": {
        "x": 10,
        "y": 24,
        "w": 84,
        "h": 70
      },
      "sourceSize": {
        "w": 100,
        "h": 100
      },
      "pivot": {
        "x": 0.5,
        "y": 0.5
      }
    },
    "24.png": {
      "frame": {
        "x": 978,
        "y": 74,
        "w": 24,
        "h": 20
      },
      "rotated": true,
      "trimmed": true,
      "spriteSourceSize": {
        "x": 52,
        "y": 36,
        "w": 24,
        "h": 20
      },
      "sourceSize": {
        "w": 100,
        "h": 100
      },
      "pivot": {
        "x": 0.5,
        "y": 0.5
      }
    },
    "04.png": {
      "frame": {
        "x": 894,
        "y": 144,
        "w": 82,
        "h": 74
      },
      "rotated": false,
      "trimmed": true,
      "spriteSourceSize": {
        "x": 10,
        "y": 18,
        "w": 82,
        "h": 74
      },
      "sourceSize": {
        "w": 100,
        "h": 100
      },
      "pivot": {
        "x": 0.5,
        "y": 0.5
      }
    },
    "22.png": {
      "frame": {
        "x": 810,
        "y": 148,
        "w": 78,
        "h": 58
      },
      "rotated": false,
      "trimmed": true,
      "spriteSourceSize": {
        "x": 16,
        "y": 24,
        "w": 78,
        "h": 58
      },
      "sourceSize": {
        "w": 100,
        "h": 100
      },
      "pivot": {
        "x": 0.5,
        "y": 0.5
      }
    },
    "03.png": {
      "frame": {
        "x": 0,
        "y": 80,
        "w": 76,
        "h": 68
      },
      "rotated": false,
      "trimmed": true,
      "spriteSourceSize": {
        "x": 12,
        "y": 20,
        "w": 76,
        "h": 68
      },
      "sourceSize": {
        "w": 100,
        "h": 100
      },
      "pivot": {
        "x": 0.5,
        "y": 0.5
      }
    },
    "02.png": {
      "frame": {
        "x": 76,
        "y": 80,
        "w": 74,
        "h": 64
      },
      "rotated": false,
      "trimmed": true,
      "spriteSourceSize": {
        "x": 14,
        "y": 22,
        "w": 74,
        "h": 64
      },
      "sourceSize": {
        "w": 100,
        "h": 100
      },
      "pivot": {
        "x": 0.5,
        "y": 0.5
      }
    },
    "23.png": {
      "frame": {
        "x": 150,
        "y": 80,
        "w": 70,
        "h": 54
      },
      "rotated": false,
      "trimmed": true,
      "spriteSourceSize": {
        "x": 20,
        "y": 24,
        "w": 70,
        "h": 54
      },
      "sourceSize": {
        "w": 100,
        "h": 100
      },
      "pivot": {
        "x": 0.5,
        "y": 0.5
      }
    },
    "01.png": {
      "frame": {
        "x": 220,
        "y": 80,
        "w": 64,
        "h": 58
      },
      "rotated": false,
      "trimmed": true,
      "spriteSourceSize": {
        "x": 18,
        "y": 24,
        "w": 64,
        "h": 58
      },
      "sourceSize": {
        "w": 100,
        "h": 100
      },
      "pivot": {
        "x": 0.5,
        "y": 0.5
      }
    },
    "00.png": {
      "frame": {
        "x": 150,
        "y": 134,
        "w": 56,
        "h": 52
      },
      "rotated": false,
      "trimmed": true,
      "spriteSourceSize": {
        "x": 22,
        "y": 26,
        "w": 56,
        "h": 52
      },
      "sourceSize": {
        "w": 100,
        "h": 100
      },
      "pivot": {
        "x": 0.5,
        "y": 0.5
      }
    }
  },
  "meta": {
    "app": "http://free-tex-packer.com",
    "version": "0.6.7",
    "image": "texture.png",
    "format": "RGBA8888",
    "size": {
      "w": 998,
      "h": 218
    },
    "scale": 1
  }
}